{
    "start": [
        [
            0,
            0
        ],
        [
            1200,
            720
        ],
        [
            500,
            720
        ],
        [
            0,
            0
        ],
        [
            1020,
            140
        ],
        [
            1200,
            620
        ],
        [
            1020,
            140
        ],
        [
            540,
            500
        ],
        [
            660,
            500
        ],
        [
            700,
            720
        ]
    ],
    "end": [
        [
            1200,
            0
        ],
        [
            1200,
            0
        ],
        [
            0,
            720
        ],
        [
            0,
            720
        ],
        [
            1020,
            620
        ],
        [
            1020,
            620
        ],
        [
            200,
            140
        ],
        [
            500,
            720
        ],
        [
            700,
            720
        ],
        [
            1200,
            720
        ]
    ],
    "thickness": [
        10,
        10,
        10,
        10,
        10,
        10,
        10,
        10,
        10,
        10
    ],
    "moves": 5,
    "victory": [
        [
            1104,
            696
        ]
    ],
    "player": [
        [
            1120,
            560
        ]
    ],
    "ball_center": [],
    "ball_radius": [],
    "portal_start": [],
    "portal_end": [],
    "coin_pos": []
}